nucleiparser/__init__.py
nucleiparser/nparse
nucleiparser/nucleiparser.py
nucleiparser-0.2.1.data/scripts/nparse
nucleiparser-0.2.1.dist-info/LICENSE
nucleiparser-0.2.1.dist-info/METADATA
nucleiparser-0.2.1.dist-info/WHEEL
nucleiparser-0.2.1.dist-info/top_level.txt
nucleiparser-0.2.1.dist-info/RECORD
