Metadata-Version: 2.1
Name: nucleiparser
Version: 0.2.1
Summary: A CLI parser for Nuclei outputs
Home-page: https://github.com/sinkmanu/nucleiparser
Author: Manuel Mancera
Author-email: Manuel Mancera <manu@unam.re>
License: GPL-3.0-or-later
Project-URL: Homepage, https://github.com/sinkmanu/nucleiparser
Project-URL: Source, https://github.com/sinkmanu/nucleiparser
Project-URL: Bug Tracker, https://github.com/sinkmanu/nucleiparser/issues
Keywords: nuclei,pentesting,nuclei parser
Classifier: Programming Language :: Python :: 3
Classifier: License :: OSI Approved :: GNU General Public License v3 or later (GPLv3+)
Classifier: Operating System :: OS Independent
Requires-Python: >=3.6
License-File: LICENSE
Requires-Dist: prettytable
